fast_sql_manager/__init__.py
fast_sql_manager/test_mysql.py
fast_sql_manager/test_sqlite.py
fast_sql_manager/abstractions/__init__.py
fast_sql_manager/abstractions/mysql.py
fast_sql_manager/abstractions/postgres.py
fast_sql_manager/abstractions/sqlite.py
fast_sql_manager/implementations/__init__.py
fast_sql_manager/implementations/mysql.py
fast_sql_manager/implementations/postgres.py
fast_sql_manager/implementations/sqlite.py
fast_sql_manager/interfaces/__init__.py
fast_sql_manager/interfaces/db_config_interface.py
fast_sql_manager-1.3.8.dist-info/LICENSE
fast_sql_manager-1.3.8.dist-info/METADATA
fast_sql_manager-1.3.8.dist-info/WHEEL
fast_sql_manager-1.3.8.dist-info/top_level.txt
fast_sql_manager-1.3.8.dist-info/RECORD
