Metadata-Version: 2.1
Name: fast-sql-manager
Version: 1.3.8
Summary: Um pacote simples para realizar operações no banco
Home-page: https://github.com/OscarSilvaOfficial/fast_sql_manager
Author: Oscar da Silva
Author-email: oscarkaka222@gmail.com
License: UNKNOWN
Platform: UNKNOWN
Classifier: Programming Language :: Python :: 3
Classifier: License :: OSI Approved :: MIT License
Classifier: Operating System :: OS Independent
Requires-Python: >=3.7
License-File: LICENSE
Requires-Dist: mysql-connector-python (>=8.0.27)
Requires-Dist: pymongo (>=4.0.1)
Requires-Dist: psycopg2-binary (>=2.9.3)
